certifi/__init__.py
certifi/__main__.py
certifi/cacert.pem
certifi/core.py
certifi-2020.4.5.dist-info/LICENSE
certifi-2020.4.5.dist-info/METADATA
certifi-2020.4.5.dist-info/WHEEL
certifi-2020.4.5.dist-info/top_level.txt
certifi-2020.4.5.dist-info/RECORD
