Metadata-Version: 1.2
Name: certifi
Version: 2020.4.5
Summary: Python package for providing Mozilla's CA Bundle.
Home-page: https://certifiio.readthedocs.io/en/latest/
Author: Kenneth Reitz
Author-email: me@kennethreitz.com
License: MPL-2.0
Project-URL: Documentation, https://certifiio.readthedocs.io/en/latest/
Project-URL: Source, https://github.com/certifi/python-certifi
Platform: UNKNOWN
Classifier: Development Status :: 5 - Production/Stable
Classifier: Intended Audience :: Developers
Classifier: License :: OSI Approved :: Mozilla Public License 2.0 (MPL 2.0)
Classifier: Natural Language :: English
Classifier: Programming Language :: Python
Classifier: Programming Language :: Python :: 2
Classifier: Programming Language :: Python :: 2.6
Classifier: Programming Language :: Python :: 2.7
Classifier: Programming Language :: Python :: 3
Classifier: Programming Language :: Python :: 3.3
Classifier: Programming Language :: Python :: 3.4
Classifier: Programming Language :: Python :: 3.5
Classifier: Programming Language :: Python :: 3.6
Classifier: Programming Language :: Python :: 3.7
Classifier: Programming Language :: Python :: 3.8
